LICENSE.txt
MANIFEST.in
README.md
requirements.txt
setup.cfg
setup.py
motion_imitation/__init__.py
motion_imitation/run.py
motion_imitation.egg-info/PKG-INFO
motion_imitation.egg-info/SOURCES.txt
motion_imitation.egg-info/dependency_links.txt
motion_imitation.egg-info/requires.txt
motion_imitation.egg-info/top_level.txt
motion_imitation/__pycache__/__init__.cpython-38.pyc
motion_imitation/data/__init__.py
motion_imitation/data/motion_imitation2.png
motion_imitation/data/motion_imitation_gif.gif
motion_imitation/data/mpc_a1.png
motion_imitation/data/motions/__init__.py
motion_imitation/data/motions/dog_backwards_pace.txt
motion_imitation/data/motions/dog_backwards_trot.txt
motion_imitation/data/motions/dog_pace.txt
motion_imitation/data/motions/dog_spin.txt
motion_imitation/data/motions/dog_trot.txt
motion_imitation/data/motions/hopturn.txt
motion_imitation/data/motions/inplace_steps.txt
motion_imitation/data/motions/runningman.txt
motion_imitation/data/motions/sidesteps.txt
motion_imitation/data/motions/turn.txt
motion_imitation/data/policies/dog_pace.zip
motion_imitation/data/policies/dog_spin.zip
motion_imitation/data/policies/dog_trot.zip
motion_imitation/envs/__init__.py
motion_imitation/envs/env_builder.py
motion_imitation/envs/locomotion_gym_config.py
motion_imitation/envs/locomotion_gym_env.py
motion_imitation/envs/__pycache__/__init__.cpython-38.pyc
motion_imitation/envs/__pycache__/env_builder.cpython-38.pyc
motion_imitation/envs/__pycache__/locomotion_gym_config.cpython-38.pyc
motion_imitation/envs/__pycache__/locomotion_gym_env.cpython-38.pyc
motion_imitation/envs/env_wrappers/__init__.py
motion_imitation/envs/env_wrappers/default_task.py
motion_imitation/envs/env_wrappers/imitation_task.py
motion_imitation/envs/env_wrappers/imitation_terminal_conditions.py
motion_imitation/envs/env_wrappers/imitation_wrapper_env.py
motion_imitation/envs/env_wrappers/observation_dictionary_to_array_wrapper.py
motion_imitation/envs/env_wrappers/simple_forward_task.py
motion_imitation/envs/env_wrappers/simple_openloop.py
motion_imitation/envs/env_wrappers/survival_task.py
motion_imitation/envs/env_wrappers/trajectory_generator_wrapper_env.py
